libFTP/__init__.py
libFTP/libFTP.py
libFTP-0.4.dist-info/METADATA
libFTP-0.4.dist-info/WHEEL
libFTP-0.4.dist-info/top_level.txt
libFTP-0.4.dist-info/RECORD
