Metadata-Version: 2.1
Name: libFTP
Version: 0.4
Summary: A small example package FTP
Home-page: https://github.com/bluebox-dev/libFTP
Author: blueboxdev
Author-email: thanakorn.vsalab@gmail.com
License: UNKNOWN
Platform: UNKNOWN
Classifier: Programming Language :: Python :: 3
Classifier: License :: OSI Approved :: MIT License
Classifier: Operating System :: OS Independent
